mintamazontagger/__init__.py
mintamazontagger/algorithm_u.py
mintamazontagger/amazon.py
mintamazontagger/amazon_test.py
mintamazontagger/args.py
mintamazontagger/category.py
mintamazontagger/category_test.py
mintamazontagger/cli.py
mintamazontagger/currency.py
mintamazontagger/currency_test.py
mintamazontagger/gift_card_parser.py
mintamazontagger/main.py
mintamazontagger/mint.py
mintamazontagger/mint_test.py
mintamazontagger/mintclient.py
mintamazontagger/mockdata.py
mintamazontagger/my_progress.py
mintamazontagger/qt.py
mintamazontagger/repro_selenium_issue.py
mintamazontagger/tagger.py
mintamazontagger/tagger_test.py
mintamazontagger/webdriver.py
mint_amazon_tagger-1.66.dist-info/LICENSE
mint_amazon_tagger-1.66.dist-info/LICENSE.chromedriver
mint_amazon_tagger-1.66.dist-info/METADATA
mint_amazon_tagger-1.66.dist-info/WHEEL
mint_amazon_tagger-1.66.dist-info/entry_points.txt
mint_amazon_tagger-1.66.dist-info/top_level.txt
mint_amazon_tagger-1.66.dist-info/RECORD
