Metadata-Version: 2.1
Name: mint-amazon-tagger
Version: 1.66
Summary: Fetches your Amazon order history and matching/tags your Mint transactions
Home-page: https://github.com/jprouty/mint-amazon-tagger
Author: Jeff Prouty
Author-email: jeff.prouty@gmail.com
Keywords: amazon mint tagger transactions order history
Classifier: Programming Language :: Python :: 3
Classifier: License :: OSI Approved :: MIT License
Classifier: Operating System :: OS Independent
Classifier: Topic :: Office/Business :: Financial
Requires-Python: >=3
License-File: LICENSE
License-File: LICENSE.chromedriver
Requires-Dist: PyQt6
Requires-Dist: mintapi >=2.12
Requires-Dist: mock
Requires-Dist: oathtool
Requires-Dist: outdated
Requires-Dist: psutil
Requires-Dist: progress
Requires-Dist: range-key-dict
Requires-Dist: requests
Requires-Dist: readchar
Requires-Dist: selenium
Requires-Dist: selenium-requests >=2.0.3
